django_slack_tools/__init__.py
django_slack_tools/app_settings.py
django_slack_tools/py.typed
django_slack_tools/locale/ko_KR/LC_MESSAGES/django.po
django_slack_tools/messenger/__init__.py
django_slack_tools/messenger/messenger.py
django_slack_tools/messenger/request.py
django_slack_tools/messenger/response.py
django_slack_tools/messenger/shortcuts.py
django_slack_tools/messenger/backends/__init__.py
django_slack_tools/messenger/backends/base.py
django_slack_tools/messenger/backends/dummy.py
django_slack_tools/messenger/backends/logging_.py
django_slack_tools/messenger/backends/slack.py
django_slack_tools/messenger/message_templates/__init__.py
django_slack_tools/messenger/message_templates/base.py
django_slack_tools/messenger/message_templates/python.py
django_slack_tools/messenger/middlewares/__init__.py
django_slack_tools/messenger/middlewares/base.py
django_slack_tools/messenger/template_loaders/__init__.py
django_slack_tools/messenger/template_loaders/base.py
django_slack_tools/messenger/template_loaders/errors.py
django_slack_tools/slack_events/__init__.py
django_slack_tools/slack_events/views.py
django_slack_tools/slack_messages/__init__.py
django_slack_tools/slack_messages/apps.py
django_slack_tools/slack_messages/shortcuts.py
django_slack_tools/slack_messages/tasks.py
django_slack_tools/slack_messages/validators.py
django_slack_tools/slack_messages/admin/__init__.py
django_slack_tools/slack_messages/admin/mention.py
django_slack_tools/slack_messages/admin/message.py
django_slack_tools/slack_messages/admin/message_recipient.py
django_slack_tools/slack_messages/admin/messaging_policy.py
django_slack_tools/slack_messages/messenger/__init__.py
django_slack_tools/slack_messages/messenger/message_templates.py
django_slack_tools/slack_messages/messenger/middlewares.py
django_slack_tools/slack_messages/messenger/template_loaders.py
django_slack_tools/slack_messages/migrations/0001_initial.py
django_slack_tools/slack_messages/migrations/0002_default_policy.py
django_slack_tools-0.3.3.dist-info/METADATA
django_slack_tools-0.3.3.dist-info/WHEEL
django_slack_tools-0.3.3.dist-info/licenses/LICENSE
django_slack_tools-0.3.3.dist-info/RECORD
