Metadata-Version: 2.4
Name: django-slack-tools
Version: 0.3.3
Summary: Little helpers working with Slack bot 🤖 in Django.
Project-URL: Homepage, https://github.com/lasuillard/django-slack-tools
Project-URL: Repository, https://github.com/lasuillard/django-slack-tools.git
Project-URL: Issues, https://github.com/lasuillard/django-slack-tools/issues
Author-email: Yuchan Lee <lasuillard@gmail.com>
License-Expression: MIT
License-File: LICENSE
Requires-Python: <4.0,>=3.9
Requires-Dist: django<5.2,>=4.2
Requires-Dist: pydantic<3,>=2
Requires-Dist: slack-bolt<2,>=1
Requires-Dist: xmltodict<1,>=0.14.1
Provides-Extra: celery
Requires-Dist: celery<6,>=5; extra == 'celery'
